llmschema/__init__.py
llmschema/core.py
llmschema/exceptions.py
llmschema/llm_client.py
llmschema/sample.py
llmschema/schema_manager.py
llmschema-0.3.dist-info/METADATA
llmschema-0.3.dist-info/WHEEL
llmschema-0.3.dist-info/top_level.txt
llmschema-0.3.dist-info/RECORD
