Metadata-Version: 2.2
Name: llmschema
Version: 0.3
Summary: A structured response wrapper for LLMs using Pydantic.
Home-page: https://github.com/shreyanssoni/llmschema
Author: Shreyans Soni
Author-email: sonishreyans01@gmail.com
Classifier: Programming Language :: Python :: 3
Classifier: License :: OSI Approved :: MIT License
Classifier: Operating System :: OS Independent
Requires-Python: >=3.7
Requires-Dist: pydantic>=2.0.0
Requires-Dist: ollama>=0.1.0
Dynamic: author
Dynamic: author-email
Dynamic: classifier
Dynamic: description
Dynamic: description-content-type
Dynamic: home-page
Dynamic: requires-dist
Dynamic: requires-python
Dynamic: summary
